talisker/__init__.py
talisker/__main__.py
talisker/celery.py
talisker/context.py
talisker/django.py
talisker/endpoints.py
talisker/flask.py
talisker/gunicorn.py
talisker/logs.py
talisker/postgresql.py
talisker/request_id.py
talisker/requests.py
talisker/revision.py
talisker/sentry.py
talisker/statsd.py
talisker/util.py
talisker/wsgi.py
talisker/logstash/talisker.filter
talisker/logstash/talisker.pattern
talisker_fork-0.10.1.dist-info/DESCRIPTION.rst
talisker_fork-0.10.1.dist-info/METADATA
talisker_fork-0.10.1.dist-info/RECORD
talisker_fork-0.10.1.dist-info/WHEEL
talisker_fork-0.10.1.dist-info/entry_points.txt
talisker_fork-0.10.1.dist-info/metadata.json
talisker_fork-0.10.1.dist-info/top_level.txt
