Metadata-Version: 2.0
Name: talisker-fork
Version: 0.10.1
Summary: A common WSGI stack
Home-page: https://github.com/canonical-ols/talisker
Author: Simon Davy
Author-email: simon.davy@canonical.com
License: GPL3
Keywords: talisker
Platform: UNKNOWN
Classifier: Development Status :: 4 - Beta
Classifier: Intended Audience :: Developers
Classifier: Natural Language :: English
Classifier: Topic :: Internet :: WWW/HTTP :: WSGI
Classifier: Topic :: Internet :: WWW/HTTP :: WSGI :: Middleware
Classifier: Topic :: System :: Logging
Classifier: Programming Language :: Python :: 2.7
Classifier: Programming Language :: Python :: 3.4
Classifier: Programming Language :: Python :: 3.5
Classifier: Programming Language :: Python :: 3.6
Classifier: Programming Language :: Python :: Implementation :: CPython
Requires-Dist: Werkzeug (>=0.11.5,<0.13)
Requires-Dist: future (>=0.15.2,<0.17)
Requires-Dist: gunicorn (<20.0,>=19.5.0)
Requires-Dist: ipaddress (>=1.0.16,<2.0)
Requires-Dist: raven (>=5.27.0,<7.0)
Requires-Dist: requests (<3.0,>=2.10.0)
Requires-Dist: statsd (>=3.2.1,<4.0)
Provides-Extra: celery
Requires-Dist: celery (>=3.1.13.0,<5.0); extra == 'celery'
Provides-Extra: dev
Requires-Dist: logging-tree; extra == 'dev'
Requires-Dist: pygments; extra == 'dev'
Provides-Extra: django
Requires-Dist: django (<1.11,>=1.8); extra == 'django'
Provides-Extra: flask
Requires-Dist: blinker (>=1.4,<2.0); extra == 'flask'
Requires-Dist: flask (>=0.11,<0.13); extra == 'flask'
Provides-Extra: pg
Requires-Dist: psycopg2 (<3.0,>=2.4.5); extra == 'pg'
Requires-Dist: sqlparse (>=0.2); extra == 'pg'
Provides-Extra: prometheus
Requires-Dist: prometheus-client (<0.1,>=0.0.17); extra == 'prometheus'
